ultimate_hosts_blacklist/deployment_launcher/__init__.py
ultimate_hosts_blacklist/deployment_launcher/cli.py
ultimate_hosts_blacklist/deployment_launcher/deployer.py
ultimate_hosts_blacklist/deployment_launcher/generator.py
ultimate_hosts_blacklist/deployment_launcher/orchester.py
ultimate_hosts_blacklist/deployment_launcher/data/__init__.py
ultimate_hosts_blacklist/deployment_launcher/data/templates/README_template.md
ultimate_hosts_blacklist/deployment_launcher/data/templates/__init__.py
ultimate_hosts_blacklist/deployment_launcher/data/templates/hosts.template
ultimate_hosts_blacklist/deployment_launcher/data/templates/hosts.windows.template
ultimate_hosts_blacklist/deployment_launcher/data/templates/hostsdeny.template
ultimate_hosts_blacklist/deployment_launcher/data/templates/superhostsdeny.template
ultimate_hosts_blacklist/deployment_launcher/defaults/__init__.py
ultimate_hosts_blacklist/deployment_launcher/defaults/hubgit.py
ultimate_hosts_blacklist/deployment_launcher/defaults/infrastructure.py
ultimate_hosts_blacklist/deployment_launcher/defaults/outputs.py
ultimate_hosts_blacklist_deployment_launcher-2.0.1.dist-info/licenses/LICENSE
ultimate_hosts_blacklist_deployment_launcher-2.0.1.dist-info/METADATA
ultimate_hosts_blacklist_deployment_launcher-2.0.1.dist-info/WHEEL
ultimate_hosts_blacklist_deployment_launcher-2.0.1.dist-info/entry_points.txt
ultimate_hosts_blacklist_deployment_launcher-2.0.1.dist-info/top_level.txt
ultimate_hosts_blacklist_deployment_launcher-2.0.1.dist-info/RECORD
