Metadata-Version: 2.4
Name: ultimate-hosts-blacklist-deployment-launcher
Version: 2.0.1
Summary: The deployment launcher of the Ultimate Hosts Blacklist project.
Home-page: https://github.com/Ultimate-Hosts-Blacklist/dev-center/tree/central-repo-updater
Author: funilrys
Author-email: contact@funilrys.com
License: MIT
Keywords: Ultimate Hosts Blacklist
Platform: any
Classifier: Environment :: Console
Classifier: Topic :: Internet
Classifier: Development Status :: 5 - Production/Stable
Classifier: Intended Audience :: Developers
Classifier: Programming Language :: Python
Classifier: Programming Language :: Python :: 3
Classifier: License :: OSI Approved :: MIT License
License-File: LICENSE
Requires-Dist: PyFunceble==4.2.28
Requires-Dist: ultimate-hosts-blacklist-whitelist
Requires-Dist: colorama
Requires-Dist: PyGithub
Dynamic: author
Dynamic: author-email
Dynamic: classifier
Dynamic: description
Dynamic: description-content-type
Dynamic: home-page
Dynamic: keywords
Dynamic: license
Dynamic: license-file
Dynamic: platform
Dynamic: requires-dist
Dynamic: summary
